nest_sdk_python_test_v1/__init__.py
nest_sdk_python_test_v1/_hooks/__init__.py
nest_sdk_python_test_v1/_hooks/sdkhooks.py
nest_sdk_python_test_v1/_hooks/types.py
nest_sdk_python_test_v1/_version.py
nest_sdk_python_test_v1/basesdk.py
nest_sdk_python_test_v1/github.py
nest_sdk_python_test_v1/httpclient.py
nest_sdk_python_test_v1/models/__init__.py
nest_sdk_python_test_v1/models/apierror.py
nest_sdk_python_test_v1/models/chapterschema.py
nest_sdk_python_test_v1/models/committeeschema.py
nest_sdk_python_test_v1/models/eventschema.py
nest_sdk_python_test_v1/models/get_userop.py
nest_sdk_python_test_v1/models/issueschema.py
nest_sdk_python_test_v1/models/labelschema.py
nest_sdk_python_test_v1/models/list_chaptersop.py
nest_sdk_python_test_v1/models/list_committeesop.py
nest_sdk_python_test_v1/models/list_eventsop.py
nest_sdk_python_test_v1/models/list_issuesop.py
nest_sdk_python_test_v1/models/list_labelsop.py
nest_sdk_python_test_v1/models/list_organizationsop.py
nest_sdk_python_test_v1/models/list_projectsop.py
nest_sdk_python_test_v1/models/list_releasesop.py
nest_sdk_python_test_v1/models/list_repositoriesop.py
nest_sdk_python_test_v1/models/list_usersop.py
nest_sdk_python_test_v1/models/no_response_error.py
nest_sdk_python_test_v1/models/organizationschema.py
nest_sdk_python_test_v1/models/pagedchapterschema.py
nest_sdk_python_test_v1/models/pagedcommitteeschema.py
nest_sdk_python_test_v1/models/pagedeventschema.py
nest_sdk_python_test_v1/models/pagedissueschema.py
nest_sdk_python_test_v1/models/pagedlabelschema.py
nest_sdk_python_test_v1/models/pagedorganizationschema.py
nest_sdk_python_test_v1/models/pagedprojectschema.py
nest_sdk_python_test_v1/models/pagedreleaseschema.py
nest_sdk_python_test_v1/models/pagedrepositoryschema.py
nest_sdk_python_test_v1/models/pageduserschema.py
nest_sdk_python_test_v1/models/projectlevel.py
nest_sdk_python_test_v1/models/projectschema.py
nest_sdk_python_test_v1/models/releaseschema.py
nest_sdk_python_test_v1-3.13.1.dist-info/METADATA
nest_sdk_python_test_v1-3.13.1.dist-info/WHEEL
nest_sdk_python_test_v1-3.13.1.dist-info/RECORD
